README.rst
setup.py
django_nox/__init__.py
django_nox/apps.py
django_nox/middleware.py
django_nox/models.py
django_nox/tests.py
django_nox/views.py
django_nox.egg-info/PKG-INFO
django_nox.egg-info/SOURCES.txt
django_nox.egg-info/dependency_links.txt
django_nox.egg-info/not-zip-safe
django_nox.egg-info/requires.txt
django_nox.egg-info/top_level.txt
django_nox/management/__init__.py
django_nox/management/commands/__init__.py
django_nox/management/commands/nox_analyze.py
django_nox/migrations/0001_initial.py
django_nox/migrations/__init__.py