Metadata-Version: 1.1
Name: django-nox
Version: 0.0.2
Summary: Statistics middleware and analysis tools for django
Home-page: https://github.com/destino74/django-nox
Author: destino74
Author-email: ljf6670601@gmail.com
License: MIT
Platform: UNKNOWN
Classifier: Development Status :: 3 - Alpha
Classifier: Intended Audience :: Developers
Classifier: License :: OSI Approved :: MIT License
Classifier: Operating System :: OS Independent
Classifier: Programming Language :: Python :: 2.7
